examples/__init__.py
examples/demo.py
examples/demo_advanced.py
examples/demo_basic.py
examples/demo_smart_reader.py
wlibrary-1.1.0.dist-info/licenses/LICENSE
wlibrary-1.1.0.dist-info/METADATA
wlibrary-1.1.0.dist-info/WHEEL
wlibrary-1.1.0.dist-info/entry_points.txt
wlibrary-1.1.0.dist-info/top_level.txt
wlibrary-1.1.0.dist-info/RECORD
