Metadata-Version: 2.4
Name: wlibrary
Version: 1.1.0
Summary: Python library for intelligent Excel file processing with automatic data cleaning and type detection
Home-page: https://github.com/Zonda001/wlibrary
Author: Sidorov Denis
Author-email: Denys Sidorov <sidorovdenys9@gmail.com>
License: MIT
Project-URL: Homepage, https://github.com/Zonda001/wlibrary
Project-URL: Repository, https://github.com/Zonda001/wlibrary
Project-URL: Bug Reports, https://github.com/Zonda001/wlibrary/issues
Keywords: excel,pandas,data-cleaning,data-analysis,type-detection,quality-metrics
Classifier: Development Status :: 4 - Beta
Classifier: Intended Audience :: Developers
Classifier: Intended Audience :: Science/Research
Classifier: Topic :: Software Development :: Libraries :: Python Modules
Classifier: Topic :: Office/Business :: Financial :: Spreadsheet
Classifier: License :: OSI Approved :: MIT License
Classifier: Programming Language :: Python :: 3
Classifier: Programming Language :: Python :: 3.10
Classifier: Programming Language :: Python :: 3.11
Classifier: Programming Language :: Python :: 3.12
Classifier: Operating System :: OS Independent
Requires-Python: >=3.10
License-File: LICENSE
Requires-Dist: pandas>=2.0.0
Requires-Dist: openpyxl>=3.0.0
Requires-Dist: numpy>=1.24.0
Provides-Extra: dev
Requires-Dist: pytest>=7.0.0; extra == "dev"
Requires-Dist: pytest-cov>=4.0.0; extra == "dev"
Provides-Extra: all
Requires-Dist: pyyaml>=6.0; extra == "all"
Requires-Dist: tqdm>=4.65.0; extra == "all"
Dynamic: author
Dynamic: home-page
Dynamic: license-file
Dynamic: requires-python
